pbl/__init__.py
pbl/cache_manager.py
pbl/echonest_plugs.py
pbl/engine.py
pbl/exper.py
pbl/frog.py
pbl/leveldb_cache.py
pbl/nocache.py
pbl/redis_cache.py
pbl/spotify_plugs.py
pbl/standard_plugs.py
pbl/test.py
pbl/track_manager.py
pbl/utils.py
pbl-1.1.6.dist-info/LICENSE.txt
pbl-1.1.6.dist-info/METADATA
pbl-1.1.6.dist-info/WHEEL
pbl-1.1.6.dist-info/top_level.txt
pbl-1.1.6.dist-info/RECORD
