Metadata-Version: 2.1
Name: pbl
Version: 1.1.6
Summary: A Python library for building playlists
Home-page: http://pbl.readthedocs.org/
Author: @plamere
Author-email: paul@spotify.com
License: LICENSE.txt
Platform: UNKNOWN
Requires-Dist: requests (>=2.5)
Requires-Dist: pyen (>=2.3)
Requires-Dist: spotipy (>=2.0)
